ds_package/__init__.py
ds_package/feature_extraction.py
ds_package/train.py
ds_package/utils.py
ds_package/validation.py
ds_package_vladimir19907-0.1.1.dist-info/METADATA
ds_package_vladimir19907-0.1.1.dist-info/WHEEL
ds_package_vladimir19907-0.1.1.dist-info/top_level.txt
ds_package_vladimir19907-0.1.1.dist-info/RECORD
